{
    "swagger": "2.0",
    "info": {
        "description": "This is a server ecommerce.",
        "title": "Swagger Golang Ecommerce",
        "contact": {
            "name": "Nguyễn Đại Nghĩa",
            "url": "https://www.facebook.com/shy.leopard.beo",
            "email": "nghiabeo1605@gmail.com"
        }
    },
    "host": "localhost:8080",
    "basePath": "/api",
    "paths": {},
    "externalDocs": {
        "description": "OpenAPI",
        "url": "https://swagger.io/resources/open-api/"
    }
}